geopy/__init__.py
geopy/adapters.py
geopy/compat.py
geopy/distance.py
geopy/exc.py
geopy/format.py
geopy/location.py
geopy/point.py
geopy/timezone.py
geopy/units.py
geopy/util.py
geopy/extra/__init__.py
geopy/extra/rate_limiter.py
geopy/geocoders/__init__.py
geopy/geocoders/algolia.py
geopy/geocoders/arcgis.py
geopy/geocoders/azure.py
geopy/geocoders/baidu.py
geopy/geocoders/banfrance.py
geopy/geocoders/base.py
geopy/geocoders/bing.py
geopy/geocoders/databc.py
geopy/geocoders/dot_us.py
geopy/geocoders/geocodeearth.py
geopy/geocoders/geocodefarm.py
geopy/geocoders/geocodio.py
geopy/geocoders/geokeo.py
geopy/geocoders/geolake.py
geopy/geocoders/geonames.py
geopy/geocoders/google.py
geopy/geocoders/googlev3.py
geopy/geocoders/here.py
geopy/geocoders/ignfrance.py
geopy/geocoders/mapbox.py
geopy/geocoders/mapquest.py
geopy/geocoders/maptiler.py
geopy/geocoders/mapzen.py
geopy/geocoders/nominatim.py
geopy/geocoders/opencage.py
geopy/geocoders/openmapquest.py
geopy/geocoders/osm.py
geopy/geocoders/pelias.py
geopy/geocoders/photon.py
geopy/geocoders/pickpoint.py
geopy/geocoders/placefinder.py
geopy/geocoders/smartystreets.py
geopy/geocoders/tomtom.py
geopy/geocoders/what3words.py
geopy/geocoders/woosmap.py
geopy/geocoders/yandex.py
geopy-2.4.0.dist-info/AUTHORS
geopy-2.4.0.dist-info/LICENSE
geopy-2.4.0.dist-info/METADATA
geopy-2.4.0.dist-info/WHEEL
geopy-2.4.0.dist-info/top_level.txt
geopy-2.4.0.dist-info/RECORD
