Metadata-Version: 2.1
Name: geopy
Version: 2.4.0
Summary: Python Geocoding Toolbox
Home-page: https://github.com/geopy/geopy
Maintainer: Kostya Esmukov
Maintainer-email: kostya@esmukov.net
License: MIT
Download-URL: https://github.com/geopy/geopy/archive/2.4.0.tar.gz
Keywords: geocode,geocoding,gis,geographical,maps,earth,distance
Platform: UNKNOWN
Classifier: Development Status :: 5 - Production/Stable
Classifier: Intended Audience :: Developers
Classifier: Intended Audience :: Science/Research
Classifier: License :: OSI Approved :: MIT License
Classifier: Operating System :: OS Independent
Classifier: Programming Language :: Python
Classifier: Topic :: Scientific/Engineering :: GIS
Classifier: Topic :: Software Development :: Libraries :: Python Modules
Classifier: Programming Language :: Python :: 3 :: Only
Classifier: Programming Language :: Python :: 3
Classifier: Programming Language :: Python :: 3.7
Classifier: Programming Language :: Python :: 3.8
Classifier: Programming Language :: Python :: 3.9
Classifier: Programming Language :: Python :: 3.10
Classifier: Programming Language :: Python :: 3.11
Classifier: Programming Language :: Python :: 3.12
Classifier: Programming Language :: Python :: Implementation :: CPython
Classifier: Programming Language :: Python :: Implementation :: PyPy
Requires-Python: >=3.7
Provides-Extra: dev
Provides-Extra: dev-lint
Provides-Extra: dev-test
Provides-Extra: dev-docs
Provides-Extra: aiohttp
Provides-Extra: requests
Provides-Extra: timezone
